chat/__init__.py
chat/admin.py
chat/apps.py
chat/models.py
chat/tests.py
chat/urls.py
chat/views.py
chat/migrations/__init__.py
realchat-1.2.dist-info/LICENSE
realchat-1.2.dist-info/METADATA
realchat-1.2.dist-info/WHEEL
realchat-1.2.dist-info/top_level.txt
realchat-1.2.dist-info/RECORD
